setup.py
airflow_pentaho/__init__.py
airflow_pentaho/plugin.py
airflow_pentaho/hooks/__init__.py
airflow_pentaho/hooks/carte.py
airflow_pentaho/hooks/kettle.py
airflow_pentaho/operators/CarteJobOperator.py
airflow_pentaho/operators/CarteTransOperator.py
airflow_pentaho/operators/KitchenOperator.py
airflow_pentaho/operators/PanOperator.py
airflow_pentaho/operators/__init__.py
airflow_pentaho/operators/carte.py
airflow_pentaho/operators/kettle.py
sample_dags/pdi_flow.py
pentaho_carte_plugin-0.0.2.dist-info/METADATA
pentaho_carte_plugin-0.0.2.dist-info/WHEEL
pentaho_carte_plugin-0.0.2.dist-info/licenses/LICENSE.txt
pentaho_carte_plugin-0.0.2.dist-info/RECORD
