Metadata-Version: 2.1
Name: pentaho-carte-plugin
Version: 0.0.2
Summary: Pentaho airflow plugin using hook
Project-URL: Homepage, https://github.com/shallowman/airflow-pentaho-plugin
Project-URL: Bug Tracker, https://github.com/shallowman/airflow-pentaho-plugin/issues
Author-email: Shallowman <feron.wu@gmail.com>
License: 
Classifier: License :: OSI Approved :: MIT License
Classifier: Operating System :: OS Independent
Classifier: Programming Language :: Python :: 3
Requires-Python: >=3.7
